codescout/__init__.py
codescout/codescout.py
codescout-0.1.10.dist-info/LICENSE
codescout-0.1.10.dist-info/METADATA
codescout-0.1.10.dist-info/WHEEL
codescout-0.1.10.dist-info/top_level.txt
codescout-0.1.10.dist-info/RECORD
