Metadata-Version: 2.1
Name: codescout
Version: 0.1.10
Summary: Permet de creer des codes scouts
Author-email: Vincent Fortin <vincent.fortin@gmail.com>
License: Apache License
Project-URL: Homepage, https://github.com/vinfort/codescout
Keywords: code,scout
Classifier: Development Status :: 3 - Alpha
Classifier: License :: OSI Approved :: Apache Software License
Classifier: Programming Language :: Python
Classifier: Programming Language :: Python :: 3
Requires-Python: >=3.6
License-File: LICENSE
Requires-Dist: pillow >=10.3.0
